rav/__init__.py
rav/__main__.py
rav/cli.py
rav/integrity.py
rav/project.py
rav/start.py
rav-0.4.3.dist-info/METADATA
rav-0.4.3.dist-info/WHEEL
rav-0.4.3.dist-info/entry_points.txt
rav-0.4.3.dist-info/RECORD
