Metadata-Version: 2.4
Name: rav
Version: 0.4.3
Summary: A cross-platform Python CLI to shortcut tp command-line commands. Inspired by Makefiles and npm scripts.
Project-URL: Homepage, https://github.com/jmitchel3/rav
Project-URL: Bug Tracker, https://github.com/jmitchel3/rav/issues
Author-email: Justin Mitchel <hello@teamcfe.com>
Classifier: License :: OSI Approved :: MIT License
Classifier: Operating System :: OS Independent
Classifier: Programming Language :: Python :: 3
Requires-Python: >=3.9
Requires-Dist: fire
Requires-Dist: pyyaml
Requires-Dist: requests
Requires-Dist: rich
Provides-Extra: dev
Requires-Dist: pytest>=7.0; extra == 'dev'
Requires-Dist: ruff>=0.2.0; extra == 'dev'
